Metadata-Version: 1.1
Name: ngg2
Version: 1.3.0
Summary: Tool to identify NGGNGG Cas9 gRNA sites in any indexed FASTA file.
Home-page: https://github.com/RobersonLab/ngg2
Author: Elisha Roberson
Author-email: dr.eli.roberson@gmail.com
License: MIT
Keywords: CRISPR Cas9 3'GG site finder
Platform: UNKNOWN
Classifier: Development Status :: 5 - Production/Stable
Classifier: Environment :: Console
Classifier: Intended Audience :: Science/Research
Classifier: License :: OSI Approved :: MIT License
Classifier: Topic :: Scientific/Engineering :: Bio-Informatics
Classifier: Programming Language :: Python :: 2.7
Classifier: Programming Language :: Python :: 3
Classifier: Programming Language :: Python :: 3.2
Classifier: Programming Language :: Python :: 3.3
Classifier: Programming Language :: Python :: 3.4
Classifier: Programming Language :: Python :: 3.5
